StoveOpt/__init__.py
StoveOpt/__main__.py
StoveOpt/_version.py
StoveOpt/create_blockmeshfile.py
StoveOpt/import_geometry.py
StoveOpt/new_case_setup.py
StoveOpt/post_processor.py
StoveOpt/run_surrounding_cases.py
StoveOpt/runner.py
StoveOpt/runner_new.py
StoveOpt/docs/.buildinfo
StoveOpt/docs/.nojekyll
StoveOpt/docs/Makefile
StoveOpt/docs/conf.py
StoveOpt/docs/genindex.html
StoveOpt/docs/index.html
StoveOpt/docs/index.rst
StoveOpt/docs/make.bat
StoveOpt/docs/objects.inv
StoveOpt/docs/py-modindex.html
StoveOpt/docs/search.html
StoveOpt/docs/searchindex.js
StoveOpt/foamfiles/blockMeshDict_OG
StoveOpt/foamfiles/counterFlowFlame2D/0_template/CH4
StoveOpt/foamfiles/counterFlowFlame2D/0_template/CO2
StoveOpt/foamfiles/counterFlowFlame2D/0_template/H2O
StoveOpt/foamfiles/counterFlowFlame2D/0_template/N2
StoveOpt/foamfiles/counterFlowFlame2D/0_template/O2
StoveOpt/foamfiles/counterFlowFlame2D/0_template/T
StoveOpt/foamfiles/counterFlowFlame2D/0_template/U_template
StoveOpt/foamfiles/counterFlowFlame2D/0_template/Ydefault
StoveOpt/foamfiles/counterFlowFlame2D/0_template/alphat
StoveOpt/foamfiles/counterFlowFlame2D/0_template/p
StoveOpt/foamfiles/counterFlowFlame2D/case_100/0/CH4
StoveOpt/foamfiles/counterFlowFlame2D/case_100/0/CO2
StoveOpt/foamfiles/counterFlowFlame2D/case_100/0/H2O
StoveOpt/foamfiles/counterFlowFlame2D/case_100/0/N2
StoveOpt/foamfiles/counterFlowFlame2D/case_100/0/O2
StoveOpt/foamfiles/counterFlowFlame2D/case_100/0/T
StoveOpt/foamfiles/counterFlowFlame2D/case_100/0/U
StoveOpt/foamfiles/counterFlowFlame2D/case_100/0/Ydefault
StoveOpt/foamfiles/counterFlowFlame2D/case_100/0/__init__.py
StoveOpt/foamfiles/counterFlowFlame2D/case_100/0/alphat
StoveOpt/foamfiles/counterFlowFlame2D/case_100/0/details
StoveOpt/foamfiles/counterFlowFlame2D/case_100/0/p
StoveOpt/foamfiles/counterFlowFlame2D/case_100/constant/__init__.py
StoveOpt/foamfiles/counterFlowFlame2D/case_100/constant/chemistryProperties
StoveOpt-0.3.10.dist-info/LICENSE
StoveOpt-0.3.10.dist-info/METADATA
StoveOpt-0.3.10.dist-info/WHEEL
StoveOpt-0.3.10.dist-info/top_level.txt
StoveOpt-0.3.10.dist-info/RECORD
