Metadata-Version: 2.1
Name: StoveOpt
Version: 0.3.10
Summary: Biomass cookstove optimization package
Home-page: https://github.com/Liam-Cassidy/StoveOpt
Author: Liam Cassidy
Author-email: cassidyl@oregonstate.edu
License: MIT
Platform: UNKNOWN
Classifier: License :: OSI Approved :: BSD License
Classifier: Natural Language :: English
Classifier: Programming Language :: Python
Requires-Python: >=2.7
